autoarray/__init__.py
autoarray/abstract_ndarray.py
autoarray/exc.py
autoarray/fixtures.py
autoarray/mock.py
autoarray/numba_util.py
autoarray/preloads.py
autoarray/type.py
autoarray/config/.gitignore
autoarray/config/README.rst
autoarray/config/general.yaml
autoarray/config/logging.yaml
autoarray/config/visualize/README.rst
autoarray/config/visualize/general.yaml
autoarray/config/visualize/mat_wrap.yaml
autoarray/config/visualize/mat_wrap_1d.yaml
autoarray/config/visualize/mat_wrap_2d.yaml
autoarray/config/visualize/plots.yaml
autoarray/dataset/__init__.py
autoarray/dataset/dataset_model.py
autoarray/dataset/grids.py
autoarray/dataset/preprocess.py
autoarray/dataset/abstract/__init__.py
autoarray/dataset/abstract/dataset.py
autoarray/dataset/abstract/w_tilde.py
autoarray/dataset/imaging/__init__.py
autoarray/dataset/imaging/dataset.py
autoarray/dataset/imaging/simulator.py
autoarray/dataset/imaging/w_tilde.py
autoarray/dataset/interferometer/__init__.py
autoarray/dataset/interferometer/dataset.py
autoarray/dataset/interferometer/simulator.py
autoarray/dataset/interferometer/w_tilde.py
autoarray/dataset/mock/__init__.py
autoarray/dataset/mock/mock_dataset.py
autoarray/dataset/plot/__init__.py
autoarray/dataset/plot/imaging_plotters.py
autoarray/dataset/plot/interferometer_plotters.py
autoarray/fit/__init__.py
autoarray/fit/fit_dataset.py
autoarray/fit/fit_imaging.py
autoarray/fit/fit_interferometer.py
autoarray/fit/fit_util.py
autoarray/fit/mock/__init__.py
autoarray/fit/mock/mock_fit_imaging.py
autoarray/fit/mock/mock_fit_interferometer.py
autoarray/fit/plot/__init__.py
autoarray/fit/plot/fit_imaging_plotters.py
autoarray/fit/plot/fit_interferometer_plotters.py
autoarray/fit/plot/fit_vector_yx_plotters.py
autoarray/geometry/__init__.py
autoarray/geometry/abstract_2d.py
autoarray/geometry/geometry_1d.py
autoarray/geometry/geometry_2d.py
autoarray/geometry/geometry_2d_irregular.py
autoarray/geometry/geometry_util.py
autoarray/inversion/__init__.py
autoarray-2026.1.21.3.dist-info/licenses/LICENSE
autoarray-2026.1.21.3.dist-info/METADATA
autoarray-2026.1.21.3.dist-info/WHEEL
autoarray-2026.1.21.3.dist-info/top_level.txt
autoarray-2026.1.21.3.dist-info/RECORD
